codpy/AAD.py
codpy/KQLearning.py
codpy/__init__.py
codpy/algs.py
codpy/clustering.py
codpy/conditioning.py
codpy/config.py
codpy/core.py
codpy/data_conversion.py
codpy/data_processing.py
codpy/dictionary.py
codpy/file.py
codpy/include_all.py
codpy/kengineering.py
codpy/kernel.py
codpy/lalg.py
codpy/metrics.py
codpy/optimization.py
codpy/parallel.py
codpy/pde.py
codpy/permutation.py
codpy/plot_utils.py
codpy/predictor.py
codpy/random_utils.py
codpy/sampling.py
codpy/selection.py
codpy/utils.py
codpy-0.2.1.dist-info/COPYING.txt
codpy-0.2.1.dist-info/METADATA
codpy-0.2.1.dist-info/WHEEL
codpy-0.2.1.dist-info/license
codpy-0.2.1.dist-info/top_level.txt
codpy-0.2.1.dist-info/RECORD
