Metadata-Version: 2.1
Name: codpy
Version: 0.2.1
Summary: An RKHS based module for numerics, statistic and machine learning
Home-page: https://github.com/smiryusupov2/codpy/tree/main
Author: jean-marc mercier
Author-email: jeanmarc.mercier@gmail.com, shohruh.miryusupov@gmail.com, max.aguirre2424b@gmail.com
Maintainer: jean-marc mercier
License: new BSD
Platform: UNKNOWN
Classifier: Development Status :: 2 - Pre-Alpha
Classifier: Environment :: Win32 (MS Windows)
Classifier: Programming Language :: Python
Classifier: Topic :: Scientific/Engineering
Classifier: Operating System :: Microsoft :: Windows :: Windows 11
License-File: license
License-File: COPYING.txt
Requires-Dist: codpydll (==0.2)
Requires-Dist: numpy (==1.24.4)
Requires-Dist: xarray (==2022.9.0)
Requires-Dist: mkl (==2022.2.1)
Requires-Dist: scikit-learn
Requires-Dist: torch (==1.13)
Requires-Dist: pandas (==1.5.0)
Requires-Dist: matplotlib (==3.6.2)
Requires-Dist: statsmodels
Requires-Dist: POT (==0.9.5)
